erasplit/__init__.py
erasplit/_config.py
erasplit/_min_dependencies.py
erasplit/__check_build/__init__.py
erasplit/_build_utils/__init__.py
erasplit/_build_utils/openmp_helpers.py
erasplit/_build_utils/pre_build_helpers.py
erasplit/_loss/__init__.py
erasplit/_loss/_loss.pxd
erasplit/_loss/link.py
erasplit/_loss/loss.py
erasplit/_loss/tests/__init__.py
erasplit/_loss/tests/test_link.py
erasplit/_loss/tests/test_loss.py
erasplit/ensemble/__init__.py
erasplit/ensemble/_hist_gradient_boosting/__init__.py
erasplit/ensemble/_hist_gradient_boosting/_bitset.pxd
erasplit/ensemble/_hist_gradient_boosting/binning.py
erasplit/ensemble/_hist_gradient_boosting/common.pxd
erasplit/ensemble/_hist_gradient_boosting/era_grower.py
erasplit/ensemble/_hist_gradient_boosting/gradient_boosting.py
erasplit/ensemble/_hist_gradient_boosting/grower.py
erasplit/ensemble/_hist_gradient_boosting/predictor.py
erasplit/ensemble/_hist_gradient_boosting/tests/__init__.py
erasplit/ensemble/_hist_gradient_boosting/tests/test_binning.py
erasplit/ensemble/_hist_gradient_boosting/tests/test_bitset.py
erasplit/ensemble/_hist_gradient_boosting/tests/test_compare_lightgbm.py
erasplit/ensemble/_hist_gradient_boosting/tests/test_gradient_boosting.py
erasplit/ensemble/_hist_gradient_boosting/tests/test_grower.py
erasplit/ensemble/_hist_gradient_boosting/tests/test_histogram.py
erasplit/ensemble/_hist_gradient_boosting/tests/test_monotonic_contraints.py
erasplit/ensemble/_hist_gradient_boosting/tests/test_predictor.py
erasplit/ensemble/_hist_gradient_boosting/tests/test_splitting.py
erasplit/ensemble/_hist_gradient_boosting/tests/test_warm_start.py
erasplit-1.0.2.dist-info/COPYING
erasplit-1.0.2.dist-info/METADATA
erasplit-1.0.2.dist-info/WHEEL
erasplit-1.0.2.dist-info/top_level.txt
erasplit-1.0.2.dist-info/RECORD
